Metadata-Version: 2.1
Name: pars-avito
Version: 0.1
Summary: Avito parser
Home-page: https://github.com/Sudox00/pars_avito
Author: soketpy
Author-email: mb_vlad@vk.com
License: UNKNOWN
Download-URL: https://github.com/Sudox00/pars_avito/tarball/master
Keywords: pars_avito,soketpy
Platform: UNKNOWN
